__init__.py
axiom_logger.py
axiom_logger-1.0.3.dist-info/LICENSE
axiom_logger-1.0.3.dist-info/METADATA
axiom_logger-1.0.3.dist-info/WHEEL
axiom_logger-1.0.3.dist-info/top_level.txt
axiom_logger-1.0.3.dist-info/RECORD
