Metadata-Version: 2.1
Name: axiom-logger
Version: 1.0.3
Summary: Python logging handler for the Axiom service
Author-email: Stefano Maddè <sm@spforniture.it>
Project-URL: Homepage, https://github.com/stemadde/axiom_logger
Project-URL: Bug Tracker, https://github.com/stemadde/axiom_logger/issues
Classifier: Programming Language :: Python :: 3
Classifier: License :: OSI Approved :: MIT License
Classifier: Operating System :: OS Independent
Requires-Python: >=3.7
License-File: LICENSE
